{
  "player_build_data": [
    {
      "type": "playerBuildTimingData",
      "msg": {
        "build_event_id": "e8beab8860e7f4f0fb6d4b46d420fad9",
        "build_player": 13435,
        "preprocess_player": 440,
        "produce_player_script_assemblies": 2009,
        "build_scripts_dlls": 38,
        "writing_asset_files": 1153,
        "postprocess_built_player": 2749,
        "node_summary_table": []
      },
      "version": 1
    },
    {
      "type": "unityLinkerData",
      "msg": {
        "build_event_id": "e8beab8860e7f4f0fb6d4b46d420fad9",
        "node_executed": false,
        "option_rule_set": "Copy"
      },
      "version": 1
    }
  ]
}